README.rst
setup.py
src/swanson/__init__.py
src/swanson/codegen.py
src/swanson/data.py
src/swanson/decorators.py
src/swanson/exceptions.py
src/swanson/handlers.py
src/swanson/models.py
src/swanson/settings.py
src/swanson/signals.py
src/swanson.egg-info/PKG-INFO
src/swanson.egg-info/SOURCES.txt
src/swanson.egg-info/dependency_links.txt
src/swanson.egg-info/requires.txt
src/swanson.egg-info/top_level.txt
src/swanson/management/__init__.py
src/swanson/management/commands/__init__.py
src/swanson/management/commands/bddgen.py
src/swanson/test/__init__.py
src/swanson/test/case.py
src/swanson/test/runner.py